bgen/__init__.py
bgen/index.py
bgen/reader.cpp
bgen/reader.cpython-38-x86_64-linux-gnu.so
bgen/reader.pyx
bgen/writer.cpp
bgen/writer.cpython-38-x86_64-linux-gnu.so
bgen/writer.pyx
bgen.libs/libgcc_s-0cd532bd.so.1
bgen.libs/libstdc++-5d72f927.so.6.0.33
bgen-1.9.7.dist-info/LICENSE.txt
bgen-1.9.7.dist-info/METADATA
bgen-1.9.7.dist-info/WHEEL
bgen-1.9.7.dist-info/top_level.txt
bgen-1.9.7.dist-info/RECORD
