Metadata-Version: 2.4
Name: bgen
Version: 1.9.7
Summary: Package for loading data from bgen files
Author-email: Jeremy McRae <jmcrae@illumina.com>
Project-URL: homepage, https://github.com/jeremymcrae/bgen
Classifier: License :: OSI Approved :: MIT License
Classifier: Development Status :: 4 - Beta
Classifier: Topic :: Scientific/Engineering :: Bio-Informatics
Requires-Python: >=3.8
License-File: LICENSE.txt
Requires-Dist: numpy
Dynamic: license-file
